quickscraper_sdk/__init__.py
quickscraper_sdk/constant.py
tests/__init__.py
tests/constant.py
tests/test_cases.py
quickscraper_sdk-1.1.2.dist-info/LICENSE
quickscraper_sdk-1.1.2.dist-info/METADATA
quickscraper_sdk-1.1.2.dist-info/WHEEL
quickscraper_sdk-1.1.2.dist-info/top_level.txt
quickscraper_sdk-1.1.2.dist-info/RECORD
