Metadata-Version: 2.1
Name: quickscraper-sdk
Version: 1.1.2
Summary: https://quickscraper.co
Home-page: https://quickscraper.co/
Author: QuickScraper
Author-email: app@quickscraper.co
License: BSD
Keywords: quickscraper
Platform: UNKNOWN
Classifier: Development Status :: 3 - Alpha
Classifier: Topic :: Utilities
Classifier: License :: OSI Approved :: BSD License
License-File: LICENSE
